{
  "Conceptos": [
    "collection"
  ],
  "lugares": null,
  "feed": {
    "id": "1058333027",
    "title": "bob's mbed",
    "Private": false,
    "tags": [
      "Remote data collection and display"
    ],
    "description": "HMI Systems",
    "feed": "https://api.xively.com/v2/feeds/1058333027.json",
    "auto_feed_url": null,
    "status": 0,
    "updated": "10/16/2013 15:39:41",
    "created": "06/28/2013 14:03:40",
    "creator": "https://xively.com/users/bobengle",
    "version": null,
    "website": null,
    "datastreams": [
      {
        "id": "orientation",
        "current_value": "left",
        "at": "10/16/2013 15:39:41",
        "max_value": "0.0",
        "min_value": "0.0",
        "tags": null,
        "unit": {
          "symbol": null,
          "label": null,
          "unitType": 0
        },
        "datapoints": null
      },
      {
        "id": "pot_1",
        "current_value": "0.093773",
        "at": "10/16/2013 15:39:41",
        "max_value": "1.0",
        "min_value": "0.000977",
        "tags": null,
        "unit": {
          "symbol": null,
          "label": null,
          "unitType": 0
        },
        "datapoints": null
      },
      {
        "id": "sample",
        "current_value": "1",
        "at": "10/16/2013 15:39:41",
        "max_value": "6313.0",
        "min_value": "1.0",
        "tags": null,
        "unit": {
          "symbol": null,
          "label": null,
          "unitType": 0
        },
        "datapoints": null
      },
      {
        "id": "side_rotation",
        "current_value": "front",
        "at": "10/16/2013 15:39:41",
        "max_value": "0.0",
        "min_value": "0.0",
        "tags": null,
        "unit": {
          "symbol": null,
          "label": null,
          "unitType": 0
        },
        "datapoints": null
      },
      {
        "id": "temperature",
        "current_value": "22.875000",
        "at": "10/16/2013 15:39:41",
        "max_value": "32.625",
        "min_value": "22.375",
        "tags": null,
        "unit": {
          "symbol": null,
          "label": null,
          "unitType": 0
        },
        "datapoints": null
      }
    ],
    "location": {
      "name": "HMI Systems",
      "domain": 0,
      "lat": "28.6527687692993",
      "lon": "-81.226601600647",
      "ele": null,
      "exposure": 0,
      "disposition": 0
    },
    "TitleHTML": "<a style=\"color: #336600; font-size:110%;\"  href=\"https://xively.com/feeds/1058333027\" >bob's mbed</a>",
    "URLMostrar": "https://xively.com/feeds/1058333027"
  },
  "pathfeed": "C:\\Users\\manzamb\\Dropbox\\Subproyectos\\IndiceSemanticoIoT\\BuscadorSemanticoIoT\\BuscadorSemantico\\WSSemanticSearch\\App_Data\\Json_Data\\1058333027.json",
  "DocumentJSON": null
}