{
  "Conceptos": [
    "parameter"
  ],
  "lugares": null,
  "feed": {
    "id": "12607",
    "title": "Parameters",
    "Private": false,
    "tags": [
      "par1",
      "par2"
    ],
    "description": "Testing on my free NXP MBED\r\n",
    "feed": "https://api.xively.com/v2/feeds/12607.json",
    "auto_feed_url": null,
    "status": 0,
    "updated": "01/06/2014 15:41:31",
    "created": "11/12/2010 12:09:09",
    "creator": "https://xively.com/users/keepitsimple",
    "version": null,
    "website": null,
    "datastreams": [
      {
        "id": "0",
        "current_value": "2.0",
        "at": "01/06/2014 15:41:31",
        "max_value": "1981.0",
        "min_value": "2.0",
        "tags": [
          "abc"
        ],
        "unit": {
          "symbol": "A",
          "label": "testen",
          "unitType": 0
        },
        "datapoints": null
      },
      {
        "id": "1",
        "current_value": "25",
        "at": "01/06/2014 15:41:31",
        "max_value": "1981.0",
        "min_value": "25.0",
        "tags": [
          "inside",
          "outside"
        ],
        "unit": {
          "symbol": "A",
          "label": "deg.",
          "unitType": 0
        },
        "datapoints": null
      },
      {
        "id": "2",
        "current_value": "1",
        "at": "01/06/2014 15:41:31",
        "max_value": "1981.0",
        "min_value": "0.0",
        "tags": [
          "tralala"
        ],
        "unit": {
          "symbol": "A",
          "label": "euro",
          "unitType": 0
        },
        "datapoints": null
      },
      {
        "id": "3",
        "current_value": "1",
        "at": "01/06/2014 15:41:31",
        "max_value": "1981.0",
        "min_value": "0.0",
        "tags": [
          "opdampn"
        ],
        "unit": {
          "symbol": "A",
          "label": "eggs",
          "unitType": 0
        },
        "datapoints": null
      }
    ],
    "location": {
      "name": "netherlands",
      "domain": 0,
      "lat": "52.379869418224",
      "lon": "6.67114734649658",
      "ele": "10",
      "exposure": 0,
      "disposition": 0
    },
    "TitleHTML": "<a style=\"color: #336600; font-size:110%;\"  href=\"https://xively.com/feeds/12607\" >Parameters</a>",
    "URLMostrar": "https://xively.com/feeds/12607"
  },
  "pathfeed": "C:\\Users\\manzamb\\Dropbox\\Subproyectos\\IndiceSemanticoIoT\\BuscadorSemanticoIoT\\BuscadorSemantico\\WSSemanticSearch\\App_Data\\Json_Data\\12607.json",
  "DocumentJSON": null
}