{
  "Conceptos": [
    "role"
  ],
  "lugares": null,
  "feed": {
    "id": "129889",
    "title": "controle_horta",
    "Private": false,
    "tags": [
      "arduino"
    ],
    "description": null,
    "feed": "https://api.xively.com/v2/feeds/129889.json",
    "auto_feed_url": null,
    "status": 0,
    "updated": "05/07/2013 14:46:19",
    "created": "05/06/2013 22:56:20",
    "creator": "https://xively.com/users/rafaelbezerra",
    "version": null,
    "website": null,
    "datastreams": [
      {
        "id": "moisture_sensor",
        "current_value": "1.00",
        "at": "05/07/2013 14:46:19",
        "max_value": "842.0",
        "min_value": "0.0",
        "tags": [
          "moisture",
          "sensor"
        ],
        "unit": {
          "symbol": null,
          "label": null,
          "unitType": 0
        },
        "datapoints": null
      }
    ],
    "location": {
      "name": null,
      "domain": 0,
      "lat": null,
      "lon": null,
      "ele": null,
      "exposure": 0,
      "disposition": 0
    },
    "TitleHTML": "<a style=\"color: #336600; font-size:110%;\"  href=\"https://xively.com/feeds/129889\" >controle_horta</a>",
    "URLMostrar": "https://xively.com/feeds/129889"
  },
  "pathfeed": "C:\\Users\\manzamb\\Dropbox\\Subproyectos\\IndiceSemanticoIoT\\BuscadorSemanticoIoT\\BuscadorSemantico\\WSSemanticSearch\\App_Data\\Json_Data\\129889.json",
  "DocumentJSON": null
}