{
  "Conceptos": [
    "right"
  ],
  "lugares": null,
  "feed": {
    "id": "1737452955",
    "title": "test  aaaa",
    "Private": false,
    "tags": null,
    "description": "CC0 1.0 Universal [http://creativecommons.org/publicdomain/zero/1.0/] To the extent possible under law, YCAM InterLab has waived all copyright and related or neighboring rights to bioelectric potential data in 'Forest Symphony'. This work is published from: Japan. \nFor more detail, please refer to our website.",
    "feed": "https://api.xively.com/v2/feeds/1737452955.json",
    "auto_feed_url": null,
    "status": 0,
    "updated": "08/01/2013 01:13:30",
    "created": "07/31/2013 02:44:40",
    "creator": "https://xively.com/users/sakai",
    "version": null,
    "website": "http://interlab.ycam.jp/en/projects/forestsymphony",
    "datastreams": [
      {
        "id": "dummy_channel",
        "current_value": "7",
        "at": "07/31/2013 07:55:32",
        "max_value": "10.0",
        "min_value": "1.0",
        "tags": null,
        "unit": {
          "symbol": null,
          "label": null,
          "unitType": 0
        },
        "datapoints": null
      }
    ],
    "location": {
      "name": "theplace",
      "domain": 0,
      "lat": "-14.4076036",
      "lon": "23.2587992",
      "ele": null,
      "exposure": 0,
      "disposition": 0
    },
    "TitleHTML": "<a style=\"color: #336600; font-size:110%;\"  href=\"https://xively.com/feeds/1737452955\" >test  aaaa</a>",
    "URLMostrar": "https://xively.com/feeds/1737452955"
  },
  "pathfeed": "C:\\Users\\manzamb\\Dropbox\\Subproyectos\\IndiceSemanticoIoT\\BuscadorSemanticoIoT\\BuscadorSemantico\\WSSemanticSearch\\App_Data\\Json_Data\\1737452955.json",
  "DocumentJSON": null
}