{
  "Conceptos": [
    "sensing"
  ],
  "lugares": null,
  "feed": {
    "id": "25940",
    "title": "ssensor",
    "Private": false,
    "tags": [
      "strain"
    ],
    "description": "ssensor",
    "feed": "https://api.xively.com/v2/feeds/25940.json",
    "auto_feed_url": null,
    "status": 0,
    "updated": "06/02/2011 10:01:57",
    "created": "05/30/2011 12:41:56",
    "creator": "https://xively.com/users/worldsensing",
    "version": null,
    "website": "http://www.worldsensing.com",
    "datastreams": [
      {
        "id": "11",
        "current_value": null,
        "at": null,
        "max_value": null,
        "min_value": null,
        "tags": [
          "11"
        ],
        "unit": {
          "symbol": "V",
          "label": "Voltage",
          "unitType": 0
        },
        "datapoints": null
      },
      {
        "id": "12",
        "current_value": null,
        "at": null,
        "max_value": null,
        "min_value": null,
        "tags": [
          "12"
        ],
        "unit": {
          "symbol": "V",
          "label": "Voltage",
          "unitType": 0
        },
        "datapoints": null
      },
      {
        "id": "13",
        "current_value": null,
        "at": null,
        "max_value": null,
        "min_value": null,
        "tags": [
          "13"
        ],
        "unit": {
          "symbol": "V",
          "label": "Voltage",
          "unitType": 0
        },
        "datapoints": null
      }
    ],
    "location": {
      "name": null,
      "domain": 0,
      "lat": null,
      "lon": null,
      "ele": null,
      "exposure": 0,
      "disposition": 0
    },
    "TitleHTML": "<a style=\"color: #336600; font-size:110%;\"  href=\"https://xively.com/feeds/25940\" >ssensor</a>",
    "URLMostrar": "https://xively.com/feeds/25940"
  },
  "pathfeed": "C:\\Users\\manzamb\\Dropbox\\Subproyectos\\IndiceSemanticoIoT\\BuscadorSemanticoIoT\\BuscadorSemantico\\WSSemanticSearch\\App_Data\\Json_Data\\25940.json",
  "DocumentJSON": null
}