{
  "Conceptos": [
    "method"
  ],
  "lugares": null,
  "feed": {
    "id": "50436",
    "title": "Twitter stats for Nick van de Giesen",
    "Private": false,
    "tags": [
      "twitter",
      "twitter_stats"
    ],
    "description": "Twitter stats for Nick van de Giesen (@nvandegiesen): Water resources management, new measurement methods, hydrology, Africa, water for food, innovation",
    "feed": "https://api.xively.com/v2/feeds/50436.json",
    "auto_feed_url": null,
    "status": 0,
    "updated": "06/12/2013 19:11:19",
    "created": "03/04/2012 16:31:10",
    "creator": "https://xively.com/users/nvandegiesen",
    "version": null,
    "website": null,
    "datastreams": [
      {
        "id": "favourites",
        "current_value": "0",
        "at": "06/12/2013 19:11:19",
        "max_value": "0.0",
        "min_value": "0.0",
        "tags": null,
        "unit": {
          "symbol": null,
          "label": "favourites",
          "unitType": 0
        },
        "datapoints": null
      },
      {
        "id": "followers",
        "current_value": "87",
        "at": "06/12/2013 19:11:19",
        "max_value": "134.0",
        "min_value": "0.0",
        "tags": null,
        "unit": {
          "symbol": null,
          "label": "followers",
          "unitType": 0
        },
        "datapoints": null
      },
      {
        "id": "followers_to_friends_ratio",
        "current_value": "1.6111111111111112",
        "at": "06/12/2013 19:11:19",
        "max_value": "2.23333333333333",
        "min_value": "0.0",
        "tags": null,
        "unit": {
          "symbol": null,
          "label": "followers_to_friends_ratio",
          "unitType": 0
        },
        "datapoints": null
      },
      {
        "id": "friends",
        "current_value": "54",
        "at": "06/12/2013 19:11:19",
        "max_value": "67.0",
        "min_value": "0.0",
        "tags": null,
        "unit": {
          "symbol": null,
          "label": "friends",
          "unitType": 0
        },
        "datapoints": null
      },
      {
        "id": "lists",
        "current_value": "2",
        "at": "06/12/2013 19:11:19",
        "max_value": "2.0",
        "min_value": "0.0",
        "tags": null,
        "unit": {
          "symbol": null,
          "label": "lists",
          "unitType": 0
        },
        "datapoints": null
      },
      {
        "id": "tweets",
        "current_value": "114",
        "at": "06/12/2013 19:11:19",
        "max_value": "114.0",
        "min_value": "0.0",
        "tags": null,
        "unit": {
          "symbol": null,
          "label": "tweets",
          "unitType": 0
        },
        "datapoints": null
      }
    ],
    "location": {
      "name": "Delft University of Technology",
      "domain": 1,
      "lat": null,
      "lon": null,
      "ele": null,
      "exposure": 0,
      "disposition": 0
    },
    "TitleHTML": "<a style=\"color: #336600; font-size:110%;\"  href=\"https://xively.com/feeds/50436\" >Twitter stats for Nick van de Giesen</a>",
    "URLMostrar": "https://xively.com/feeds/50436"
  },
  "pathfeed": "C:\\Users\\manzamb\\Dropbox\\Subproyectos\\IndiceSemanticoIoT\\BuscadorSemanticoIoT\\BuscadorSemantico\\WSSemanticSearch\\App_Data\\Json_Data\\50436.json",
  "DocumentJSON": null
}