{
  "Conceptos": [
    "frequency"
  ],
  "lugares": null,
  "feed": {
    "id": "51580",
    "title": "Aurora",
    "Private": false,
    "tags": null,
    "description": "Feed of my aurora",
    "feed": "https://api.xively.com/v2/feeds/51580.json",
    "auto_feed_url": null,
    "status": 0,
    "updated": "03/11/2012 16:33:23",
    "created": "03/11/2012 13:16:36",
    "creator": "https://xively.com/users/malcsmith",
    "version": null,
    "website": null,
    "datastreams": [
      {
        "id": "1",
        "current_value": null,
        "at": "03/11/2012 13:16:36",
        "max_value": null,
        "min_value": null,
        "tags": [
          "Array1volts"
        ],
        "unit": {
          "symbol": null,
          "label": "volts",
          "unitType": 0
        },
        "datapoints": null
      },
      {
        "id": "2",
        "current_value": null,
        "at": "03/11/2012 13:16:36",
        "max_value": null,
        "min_value": null,
        "tags": [
          "Array1Amps"
        ],
        "unit": {
          "symbol": null,
          "label": "Amps",
          "unitType": 0
        },
        "datapoints": null
      },
      {
        "id": "3",
        "current_value": null,
        "at": "03/11/2012 13:16:36",
        "max_value": null,
        "min_value": null,
        "tags": [
          "Array1Power"
        ],
        "unit": {
          "symbol": null,
          "label": "W",
          "unitType": 0
        },
        "datapoints": null
      },
      {
        "id": "4",
        "current_value": null,
        "at": "03/11/2012 13:16:36",
        "max_value": null,
        "min_value": null,
        "tags": [
          "Array2volts"
        ],
        "unit": {
          "symbol": null,
          "label": "volts",
          "unitType": 0
        },
        "datapoints": null
      },
      {
        "id": "5",
        "current_value": null,
        "at": "03/11/2012 13:16:36",
        "max_value": null,
        "min_value": null,
        "tags": [
          "Array2Amps"
        ],
        "unit": {
          "symbol": null,
          "label": "Amps",
          "unitType": 0
        },
        "datapoints": null
      },
      {
        "id": "6",
        "current_value": null,
        "at": "03/11/2012 13:16:36",
        "max_value": null,
        "min_value": null,
        "tags": [
          "Array2Power"
        ],
        "unit": {
          "symbol": null,
          "label": "W",
          "unitType": 0
        },
        "datapoints": null
      },
      {
        "id": "7",
        "current_value": null,
        "at": "03/11/2012 13:16:36",
        "max_value": null,
        "min_value": null,
        "tags": [
          "GridVolts"
        ],
        "unit": {
          "symbol": null,
          "label": "Volts",
          "unitType": 0
        },
        "datapoints": null
      },
      {
        "id": "8",
        "current_value": null,
        "at": "03/11/2012 13:16:36",
        "max_value": null,
        "min_value": null,
        "tags": [
          "GridAmps"
        ],
        "unit": {
          "symbol": null,
          "label": "Amps",
          "unitType": 0
        },
        "datapoints": null
      },
      {
        "id": "9",
        "current_value": null,
        "at": "03/11/2012 13:16:36",
        "max_value": null,
        "min_value": null,
        "tags": [
          "GridPower"
        ],
        "unit": {
          "symbol": null,
          "label": "W",
          "unitType": 0
        },
        "datapoints": null
      },
      {
        "id": "10",
        "current_value": null,
        "at": "03/11/2012 13:16:36",
        "max_value": null,
        "min_value": null,
        "tags": [
          "Frequency Grid"
        ],
        "unit": {
          "symbol": null,
          "label": "Hz",
          "unitType": 0
        },
        "datapoints": null
      },
      {
        "id": "11",
        "current_value": null,
        "at": "03/11/2012 13:16:36",
        "max_value": null,
        "min_value": null,
        "tags": [
          "Efficiency"
        ],
        "unit": {
          "symbol": null,
          "label": "%",
          "unitType": 0
        },
        "datapoints": null
      },
      {
        "id": "12",
        "current_value": null,
        "at": "03/11/2012 13:16:36",
        "max_value": null,
        "min_value": null,
        "tags": [
          "InverterTemp"
        ],
        "unit": {
          "symbol": null,
          "label": "C",
          "unitType": 0
        },
        "datapoints": null
      },
      {
        "id": "13",
        "current_value": null,
        "at": "03/11/2012 13:16:36",
        "max_value": null,
        "min_value": null,
        "tags": [
          "BoosterTemp"
        ],
        "unit": {
          "symbol": null,
          "label": "C",
          "unitType": 0
        },
        "datapoints": null
      },
      {
        "id": "14",
        "current_value": null,
        "at": "03/11/2012 13:16:36",
        "max_value": null,
        "min_value": null,
        "tags": [
          "Power"
        ],
        "unit": {
          "symbol": null,
          "label": "W",
          "unitType": 0
        },
        "datapoints": null
      },
      {
        "id": "15",
        "current_value": null,
        "at": null,
        "max_value": null,
        "min_value": null,
        "tags": [
          "xx"
        ],
        "unit": {
          "symbol": null,
          "label": "xx",
          "unitType": 0
        },
        "datapoints": null
      },
      {
        "id": "16",
        "current_value": null,
        "at": null,
        "max_value": null,
        "min_value": null,
        "tags": [
          "xx"
        ],
        "unit": {
          "symbol": null,
          "label": "xx",
          "unitType": 0
        },
        "datapoints": null
      },
      {
        "id": "17",
        "current_value": null,
        "at": null,
        "max_value": null,
        "min_value": null,
        "tags": [
          "xx"
        ],
        "unit": {
          "symbol": null,
          "label": "xx",
          "unitType": 0
        },
        "datapoints": null
      },
      {
        "id": "18",
        "current_value": null,
        "at": null,
        "max_value": null,
        "min_value": null,
        "tags": [
          "PowerThismonth"
        ],
        "unit": {
          "symbol": null,
          "label": "kwH",
          "unitType": 0
        },
        "datapoints": null
      },
      {
        "id": "19",
        "current_value": null,
        "at": null,
        "max_value": null,
        "min_value": null,
        "tags": [
          "Powerthisyear"
        ],
        "unit": {
          "symbol": null,
          "label": "kwH",
          "unitType": 0
        },
        "datapoints": null
      },
      {
        "id": "20",
        "current_value": null,
        "at": null,
        "max_value": null,
        "min_value": null,
        "tags": [
          "PowerSincereset"
        ],
        "unit": {
          "symbol": null,
          "label": "kwH",
          "unitType": 0
        },
        "datapoints": null
      }
    ],
    "location": {
      "name": null,
      "domain": 0,
      "lat": "53.432293263193",
      "lon": "-2.3261833190918",
      "ele": null,
      "exposure": 1,
      "disposition": 0
    },
    "TitleHTML": "<a style=\"color: #336600; font-size:110%;\"  href=\"https://xively.com/feeds/51580\" >Aurora</a>",
    "URLMostrar": "https://xively.com/feeds/51580"
  },
  "pathfeed": "C:\\Users\\manzamb\\Dropbox\\Subproyectos\\IndiceSemanticoIoT\\BuscadorSemanticoIoT\\BuscadorSemantico\\WSSemanticSearch\\App_Data\\Json_Data\\51580.json",
  "DocumentJSON": null
}