{
  "Conceptos": [
    "wind vane"
  ],
  "lugares": null,
  "feed": {
    "id": "55063",
    "title": "SCALe office Anemoscope",
    "Private": false,
    "tags": null,
    "description": "DIY Anemoscope (windvane+direction) data",
    "feed": "https://api.xively.com/v2/feeds/55063.json",
    "auto_feed_url": null,
    "status": 0,
    "updated": "04/10/2012 10:25:39",
    "created": "04/08/2012 06:47:27",
    "creator": "https://xively.com/users/doyoungju",
    "version": null,
    "website": "http://www.scale.kr/",
    "datastreams": [
      {
        "id": "0",
        "current_value": "0.515548",
        "at": "04/10/2012 10:25:39",
        "max_value": "0.721",
        "min_value": "0.131",
        "tags": null,
        "unit": {
          "symbol": null,
          "label": null,
          "unitType": 0
        },
        "datapoints": null
      },
      {
        "id": "1",
        "current_value": "0.182327",
        "at": "04/10/2012 10:25:39",
        "max_value": "0.85",
        "min_value": "0.015",
        "tags": null,
        "unit": {
          "symbol": null,
          "label": null,
          "unitType": 0
        },
        "datapoints": null
      }
    ],
    "location": {
      "name": "SCALe.kr Office",
      "domain": 0,
      "lat": "37.5400764467514",
      "lon": "126.992245911724",
      "ele": "20",
      "exposure": 1,
      "disposition": 0
    },
    "TitleHTML": "<a style=\"color: #336600; font-size:110%;\"  href=\"https://xively.com/feeds/55063\" >SCALe office Anemoscope</a>",
    "URLMostrar": "https://xively.com/feeds/55063"
  },
  "pathfeed": "C:\\Users\\manzamb\\Dropbox\\Subproyectos\\IndiceSemanticoIoT\\BuscadorSemanticoIoT\\BuscadorSemantico\\WSSemanticSearch\\App_Data\\Json_Data\\55063.json",
  "DocumentJSON": null
}