{
  "Conceptos": [
    "platform"
  ],
  "lugares": null,
  "feed": {
    "id": "64156",
    "title": "Fridge experiment",
    "Private": false,
    "tags": [
      "Growguard sensor plant monitoring Mediamatic Saro fridge"
    ],
    "description": "Here I (Saro Van Cleynenbreugel) do experiments with the growguard plantsensor platform.",
    "feed": "https://api.xively.com/v2/feeds/64156.json",
    "auto_feed_url": null,
    "status": 0,
    "updated": "03/02/2013 19:45:59",
    "created": "06/19/2012 10:00:32",
    "creator": "https://xively.com/users/mm01",
    "version": null,
    "website": "http://Www.mediamatic.net",
    "datastreams": [
      {
        "id": "8000_temp",
        "current_value": "3.4",
        "at": "03/02/2013 19:45:59",
        "max_value": "10.1",
        "min_value": "2.4",
        "tags": null,
        "unit": {
          "symbol": null,
          "label": null,
          "unitType": 0
        },
        "datapoints": null
      },
      {
        "id": "8000_light",
        "current_value": "31",
        "at": "03/02/2013 19:45:59",
        "max_value": "100.0",
        "min_value": "0.0",
        "tags": null,
        "unit": {
          "symbol": null,
          "label": null,
          "unitType": 0
        },
        "datapoints": null
      },
      {
        "id": "8000_moist",
        "current_value": "545",
        "at": "03/02/2013 19:45:59",
        "max_value": "838.0",
        "min_value": "18.0",
        "tags": null,
        "unit": {
          "symbol": null,
          "label": null,
          "unitType": 0
        },
        "datapoints": null
      }
    ],
    "location": {
      "name": "Amsterdam",
      "domain": 0,
      "lat": "52.3723765737608",
      "lon": "4.85295295715332",
      "ele": null,
      "exposure": 0,
      "disposition": 0
    },
    "TitleHTML": "<a style=\"color: #336600; font-size:110%;\"  href=\"https://xively.com/feeds/64156\" >Fridge experiment</a>",
    "URLMostrar": "https://xively.com/feeds/64156"
  },
  "pathfeed": "C:\\Users\\manzamb\\Dropbox\\Subproyectos\\IndiceSemanticoIoT\\BuscadorSemanticoIoT\\BuscadorSemantico\\WSSemanticSearch\\App_Data\\Json_Data\\64156.json",
  "DocumentJSON": null
}