{
  "Conceptos": [
    "qualitã"
  ],
  "lugares": null,
  "feed": {
    "id": "644210100",
    "title": "Indoor Airquality",
    "Private": false,
    "tags": [
      "arduino",
      "indoor airquality",
      "temperature"
    ],
    "description": "Automatic air ventilation , Indoor air quality detector \nThis sensor is designed for comprehensive monitor over indoor air condition. It's responsive to a wide scope of harmful gases, as carbon monixide, alcohol, acetone, thinner, formaldehyde and so on. Due to the measuring mechanism, this sensor can not output specific data to describe target gases' concentrations quantitatively. But it's still competent enough to be used in applications that require only qualitative results, like auto refresher sprayers and auto air cycling systems.",
    "feed": "https://api.xively.com/v2/feeds/644210100.json",
    "auto_feed_url": null,
    "status": 0,
    "updated": "12/20/2013 12:54:19",
    "created": "07/03/2013 13:12:39",
    "creator": "https://xively.com/users/pedrothomas",
    "version": null,
    "website": "http://datalogger.gmxhome.de",
    "datastreams": [
      {
        "id": "PowerConsumption",
        "current_value": "100",
        "at": "12/20/2013 12:54:19",
        "max_value": "2000.0",
        "min_value": "0.0",
        "tags": null,
        "unit": {
          "symbol": null,
          "label": "Watt",
          "unitType": 0
        },
        "datapoints": null
      },
      {
        "id": "Sensor-AI-01-AirQualityStatus",
        "current_value": "1311",
        "at": "12/20/2013 12:54:19",
        "max_value": "5000.0",
        "min_value": "229.0",
        "tags": null,
        "unit": {
          "symbol": "Level",
          "label": null,
          "unitType": 0
        },
        "datapoints": null
      },
      {
        "id": "Sensor-AI-01-InnenAirQuality",
        "current_value": "3",
        "at": "12/20/2013 12:54:19",
        "max_value": "4.0",
        "min_value": "1.0",
        "tags": null,
        "unit": {
          "symbol": "Level",
          "label": null,
          "unitType": 0
        },
        "datapoints": null
      },
      {
        "id": "Sensor-HI-01-InnenFeuchte",
        "current_value": "33.20",
        "at": "12/20/2013 12:54:19",
        "max_value": "99.6",
        "min_value": "23.1",
        "tags": null,
        "unit": {
          "symbol": "%",
          "label": null,
          "unitType": 0
        },
        "datapoints": null
      },
      {
        "id": "Sensor-TI-01-InnenTemp",
        "current_value": "23.40",
        "at": "12/20/2013 12:54:19",
        "max_value": "34.5",
        "min_value": "9.7",
        "tags": null,
        "unit": {
          "symbol": "°C",
          "label": null,
          "unitType": 0
        },
        "datapoints": null
      }
    ],
    "location": {
      "name": "Z1 HV",
      "domain": 0,
      "lat": "48.7280584141951",
      "lon": "9.13234734552771",
      "ele": null,
      "exposure": 0,
      "disposition": 0
    },
    "TitleHTML": "<a style=\"color: #336600; font-size:110%;\"  href=\"https://xively.com/feeds/644210100\" >Indoor Airquality</a>",
    "URLMostrar": "https://xively.com/feeds/644210100"
  },
  "pathfeed": "C:\\Users\\manzamb\\Dropbox\\Subproyectos\\IndiceSemanticoIoT\\BuscadorSemanticoIoT\\BuscadorSemantico\\WSSemanticSearch\\App_Data\\Json_Data\\644210100.json",
  "DocumentJSON": null
}