{
  "Conceptos": [
    "temperatura"
  ],
  "lugares": null,
  "feed": {
    "id": "677469583",
    "title": "RegistroP1GR1",
    "Private": false,
    "tags": null,
    "description": null,
    "feed": "https://api.xively.com/v2/feeds/677469583.json",
    "auto_feed_url": null,
    "status": 0,
    "updated": "12/31/2013 12:00:08",
    "created": "07/26/2013 09:09:57",
    "creator": "https://xively.com/users/itvsoft",
    "version": null,
    "website": null,
    "datastreams": [
      {
        "id": "Local",
        "current_value": "26.94",
        "at": "12/31/2013 12:00:08",
        "max_value": "29.69",
        "min_value": "19.37",
        "tags": [
          "Temperatura"
        ],
        "unit": {
          "symbol": "Celsius",
          "label": "Grados",
          "unitType": 0
        },
        "datapoints": null
      }
    ],
    "location": {
      "name": null,
      "domain": 0,
      "lat": null,
      "lon": null,
      "ele": null,
      "exposure": 0,
      "disposition": 0
    },
    "TitleHTML": "<a style=\"color: #336600; font-size:110%;\"  href=\"https://xively.com/feeds/677469583\" >RegistroP1GR1</a>",
    "URLMostrar": "https://xively.com/feeds/677469583"
  },
  "pathfeed": "C:\\Users\\manzamb\\Dropbox\\Subproyectos\\IndiceSemanticoIoT\\BuscadorSemanticoIoT\\BuscadorSemantico\\WSSemanticSearch\\App_Data\\Json_Data\\677469583.json",
  "DocumentJSON": null
}