{
  "Conceptos": [
    "humidity"
  ],
  "lugares": null,
  "feed": {
    "id": "81913",
    "title": "Air Quality Egg",
    "Private": false,
    "tags": [
      "device:type=Air Quality Egg",
      "device:type=airqualityegg"
    ],
    "description": "trial deployment",
    "feed": "https://api.xively.com/v2/feeds/81913.json",
    "auto_feed_url": null,
    "status": 0,
    "updated": "03/17/2014 16:48:25",
    "created": "10/23/2012 23:13:47",
    "creator": "https://xively.com/users/airqualityegg",
    "version": null,
    "website": null,
    "datastreams": [
      {
        "id": "CO_00-04-a3-27-c1-b2_1",
        "current_value": "21829.73828125",
        "at": "03/17/2014 16:21:33",
        "max_value": "121566.1796875",
        "min_value": "-38617.31640625",
        "tags": [
          "aqe:data_origin=computed",
          "aqe:firmware_version=32",
          "aqe:sensor_address=00:04:a3:27:c1:b2",
          "aqe:sensor_index=1",
          "aqe:sensor_type=CO"
        ],
        "unit": {
          "symbol": "ppb",
          "label": "ppb",
          "unitType": 0
        },
        "datapoints": null
      },
      {
        "id": "CO_r0_00-04-a3-27-c1-b2_1",
        "current_value": "750000.00000000",
        "at": "03/17/2014 16:21:28",
        "max_value": "750000.0",
        "min_value": "750000.0",
        "tags": [
          "aqe:data_origin=r0",
          "aqe:firmware_version=32",
          "aqe:sensor_address=00:04:a3:27:c1:b2",
          "aqe:sensor_index=1",
          "aqe:sensor_type=CO"
        ],
        "unit": {
          "symbol": "ohms",
          "label": "ohms",
          "unitType": 0
        },
        "datapoints": null
      },
      {
        "id": "CO_raw_00-04-a3-27-c1-b2_1",
        "current_value": "159555.00000000",
        "at": "03/17/2014 16:21:23",
        "max_value": "985799.0",
        "min_value": "3599.0",
        "tags": [
          "aqe:data_origin=raw",
          "aqe:firmware_version=32",
          "aqe:sensor_address=00:04:a3:27:c1:b2",
          "aqe:sensor_index=1",
          "aqe:sensor_type=CO"
        ],
        "unit": {
          "symbol": "ohms",
          "label": "ohms",
          "unitType": 0
        },
        "datapoints": null
      },
      {
        "id": "Humidity_00-00-00-00-00-00_0",
        "current_value": "23.29999923",
        "at": "07/15/2013 13:34:48",
        "max_value": "29.70000076",
        "min_value": "23.0",
        "tags": [
          "aqe:data_origin=computed",
          "aqe:firmware_version=32",
          "aqe:sensor_address=00:00:00:00:00:00",
          "aqe:sensor_index=0",
          "aqe:sensor_type=Humidity"
        ],
        "unit": {
          "symbol": "%",
          "label": "%",
          "unitType": 0
        },
        "datapoints": null
      },
      {
        "id": "Humidity_00-04-a3-27-c2-79_0",
        "current_value": "0.00000000",
        "at": "03/17/2014 16:48:25",
        "max_value": "96.19999694",
        "min_value": "0.0",
        "tags": [
          "aqe:data_origin=computed",
          "aqe:firmware_version=32",
          "aqe:sensor_address=00:04:a3:27:c2:79",
          "aqe:sensor_index=0",
          "aqe:sensor_type=Humidity"
        ],
        "unit": {
          "symbol": "%",
          "label": "%",
          "unitType": 0
        },
        "datapoints": null
      },
      {
        "id": "NO2_00-04-a3-27-c1-b2_0",
        "current_value": "65351.25781250",
        "at": "03/17/2014 16:21:18",
        "max_value": "988928.4375",
        "min_value": "0.0",
        "tags": [
          "aqe:data_origin=computed",
          "aqe:firmware_version=32",
          "aqe:sensor_address=00:04:a3:27:c1:b2",
          "aqe:sensor_index=0",
          "aqe:sensor_type=NO2"
        ],
        "unit": {
          "symbol": "ppb",
          "label": "ppb",
          "unitType": 0
        },
        "datapoints": null
      },
      {
        "id": "NO2_r0_00-04-a3-27-c1-b2_0",
        "current_value": "2200.00000000",
        "at": "03/17/2014 16:21:13",
        "max_value": "2200.0",
        "min_value": "2200.0",
        "tags": [
          "aqe:data_origin=r0",
          "aqe:firmware_version=32",
          "aqe:sensor_address=00:04:a3:27:c1:b2",
          "aqe:sensor_index=0",
          "aqe:sensor_type=NO2"
        ],
        "unit": {
          "symbol": "ohms",
          "label": "ohms",
          "unitType": 0
        },
        "datapoints": null
      },
      {
        "id": "NO2_raw_00-04-a3-27-c1-b2_0",
        "current_value": "62271004.00000000",
        "at": "03/17/2014 16:21:08",
        "max_value": "124786208.0",
        "min_value": "0.0",
        "tags": [
          "aqe:data_origin=raw",
          "aqe:firmware_version=32",
          "aqe:sensor_address=00:04:a3:27:c1:b2",
          "aqe:sensor_index=0",
          "aqe:sensor_type=NO2"
        ],
        "unit": {
          "symbol": "ohms",
          "label": "ohms",
          "unitType": 0
        },
        "datapoints": null
      },
      {
        "id": "Temperature_00-00-00-00-00-00_1",
        "current_value": "31.89999961",
        "at": "07/15/2013 13:34:44",
        "max_value": "32.5",
        "min_value": "29.0",
        "tags": [
          "aqe:data_origin=computed",
          "aqe:firmware_version=32",
          "aqe:sensor_address=00:00:00:00:00:00",
          "aqe:sensor_index=1",
          "aqe:sensor_type=Temperature"
        ],
        "unit": {
          "symbol": "deg C",
          "label": "deg C",
          "unitType": 0
        },
        "datapoints": null
      },
      {
        "id": "Temperature_00-04-a3-27-c2-79_1",
        "current_value": "-1.00000000",
        "at": "03/17/2014 16:48:23",
        "max_value": "52.79999923",
        "min_value": "-1.0",
        "tags": [
          "aqe:data_origin=computed",
          "aqe:firmware_version=32",
          "aqe:sensor_address=00:04:a3:27:c2:79",
          "aqe:sensor_index=1",
          "aqe:sensor_type=Temperature"
        ],
        "unit": {
          "symbol": "deg C",
          "label": "deg C",
          "unitType": 0
        },
        "datapoints": null
      }
    ],
    "location": {
      "name": null,
      "domain": 0,
      "lat": "45.5315273710335",
      "lon": "-122.705139518738",
      "ele": "15",
      "exposure": 1,
      "disposition": 0
    },
    "TitleHTML": "<a style=\"color: #336600; font-size:110%;\"  href=\"https://xively.com/feeds/81913\" >Air Quality Egg</a>",
    "URLMostrar": "https://xively.com/feeds/81913"
  },
  "pathfeed": "C:\\Users\\manzamb\\Dropbox\\Subproyectos\\IndiceSemanticoIoT\\BuscadorSemanticoIoT\\BuscadorSemantico\\WSSemanticSearch\\App_Data\\Json_Data\\81913.json",
  "DocumentJSON": null
}