{
  "Conceptos": [
    "hardness"
  ],
  "lugares": null,
  "feed": {
    "id": "8318",
    "title": "TempFeedSG",
    "Private": false,
    "tags": null,
    "description": "Water Temperature",
    "feed": "https://api.xively.com/v2/feeds/8318.json",
    "auto_feed_url": null,
    "status": 0,
    "updated": "08/17/2010 13:35:26",
    "created": "06/21/2010 06:03:02",
    "creator": "https://xively.com/users/d086074",
    "version": null,
    "website": "http://www.pachube.com",
    "datastreams": [
      {
        "id": "0",
        "current_value": "20.3",
        "at": "08/12/2010 08:18:17",
        "max_value": "28.2",
        "min_value": "15.2",
        "tags": [
          "ABC Temperature Sensor"
        ],
        "unit": {
          "symbol": null,
          "label": null,
          "unitType": 0
        },
        "datapoints": null
      },
      {
        "id": "1",
        "current_value": "7.4",
        "at": "08/12/2010 08:18:17",
        "max_value": "11.5",
        "min_value": "6.1",
        "tags": [
          "ABC PH Sensor"
        ],
        "unit": {
          "symbol": null,
          "label": null,
          "unitType": 0
        },
        "datapoints": null
      },
      {
        "id": "2",
        "current_value": "9.6",
        "at": "08/12/2010 08:18:17",
        "max_value": "11.5",
        "min_value": "8.2",
        "tags": [
          "ABC Dissolved Oxygen Sensor"
        ],
        "unit": {
          "symbol": null,
          "label": null,
          "unitType": 0
        },
        "datapoints": null
      },
      {
        "id": "3",
        "current_value": "8.7",
        "at": "08/12/2010 08:18:17",
        "max_value": "8.7",
        "min_value": "8.1",
        "tags": [
          "ABC Ammonia Sensor"
        ],
        "unit": {
          "symbol": null,
          "label": null,
          "unitType": 0
        },
        "datapoints": null
      },
      {
        "id": "4",
        "current_value": null,
        "at": "08/12/2010 08:18:17",
        "max_value": null,
        "min_value": null,
        "tags": [
          "Ammonia Sensor"
        ],
        "unit": {
          "symbol": null,
          "label": null,
          "unitType": 0
        },
        "datapoints": null
      },
      {
        "id": "5",
        "current_value": null,
        "at": "08/12/2010 08:18:17",
        "max_value": null,
        "min_value": null,
        "tags": [
          "ABC Hardness Sensor"
        ],
        "unit": {
          "symbol": null,
          "label": null,
          "unitType": 0
        },
        "datapoints": null
      },
      {
        "id": "6",
        "current_value": null,
        "at": null,
        "max_value": null,
        "min_value": null,
        "tags": [
          "AAA Sensor"
        ],
        "unit": {
          "symbol": null,
          "label": null,
          "unitType": 0
        },
        "datapoints": null
      }
    ],
    "location": {
      "name": "Fish Farm",
      "domain": 1,
      "lat": "1.37933757185213",
      "lon": "103.861999511719",
      "ele": "13",
      "exposure": 1,
      "disposition": 0
    },
    "TitleHTML": "<a style=\"color: #336600; font-size:110%;\"  href=\"https://xively.com/feeds/8318\" >TempFeedSG</a>",
    "URLMostrar": "https://xively.com/feeds/8318"
  },
  "pathfeed": "C:\\Users\\manzamb\\Dropbox\\Subproyectos\\IndiceSemanticoIoT\\BuscadorSemanticoIoT\\BuscadorSemantico\\WSSemanticSearch\\App_Data\\Json_Data\\8318.json",
  "DocumentJSON": null
}