{
  "Conceptos": [
    "color"
  ],
  "lugares": null,
  "feed": {
    "id": "98494",
    "title": "Humidors",
    "Private": false,
    "tags": [
      "cedar",
      "cigar",
      "humidity",
      "humidor",
      "lounge",
      "temperature"
    ],
    "description": null,
    "feed": "https://api.xively.com/v2/feeds/98494.json",
    "auto_feed_url": null,
    "status": 0,
    "updated": "01/17/2013 22:32:41",
    "created": "01/17/2013 20:41:07",
    "creator": "https://xively.com/users/krhoyt",
    "version": null,
    "website": null,
    "datastreams": [
      {
        "id": "spcigars",
        "current_value": "-7.649",
        "at": "01/25/2013 16:42:43",
        "max_value": "76.217",
        "min_value": "-24.484",
        "tags": [
          "cigar",
          "colorado",
          "denver",
          "lounge",
          "pappas",
          "stanley"
        ],
        "unit": {
          "symbol": null,
          "label": "Farenheit",
          "unitType": 0
        },
        "datapoints": null
      }
    ],
    "location": {
      "name": "Stanley Pappas",
      "domain": 0,
      "lat": "39.5917006409679",
      "lon": "-104.878256320953",
      "ele": null,
      "exposure": 0,
      "disposition": 0
    },
    "TitleHTML": "<a style=\"color: #336600; font-size:110%;\"  href=\"https://xively.com/feeds/98494\" >Humidors</a>",
    "URLMostrar": "https://xively.com/feeds/98494"
  },
  "pathfeed": "C:\\Users\\manzamb\\Dropbox\\Subproyectos\\IndiceSemanticoIoT\\BuscadorSemanticoIoT\\BuscadorSemantico\\WSSemanticSearch\\App_Data\\Json_Data\\98494.json",
  "DocumentJSON": null
}